chempotpy/__init__.py
chempotpy/_version.py
chempotpy/ALC/1
chempotpy/ALC/2
chempotpy/ALC/ALC5m0_LEPS_ModelSurface.cpython-311-x86_64-linux-gnu.so
chempotpy/ALC/ALC5m0_LEPS_ModelSurface.f
chempotpy/ALC/ALC5m0_LEPS_ModelSurface.log
chempotpy/ALC/ALC6m0_LEPS_ModelSurface.cpython-311-x86_64-linux-gnu.so
chempotpy/ALC/ALC6m0_LEPS_ModelSurface.f
chempotpy/ALC/ALC6m0_LEPS_ModelSurface.log
chempotpy/ALC/ALC7m0_LEPS_ModelSurface.cpython-311-x86_64-linux-gnu.so
chempotpy/ALC/ALC7m0_LEPS_ModelSurface.f
chempotpy/ALC/ALC7m0_LEPS_ModelSurface.log
chempotpy/ALC/ALC7m10_LEPS_ModelSurface.cpython-311-x86_64-linux-gnu.so
chempotpy/ALC/ALC7m10_LEPS_ModelSurface.f
chempotpy/ALC/ALC7m10_LEPS_ModelSurface.log
chempotpy/ALC/ALC7m1_LEPS_ModelSurface.cpython-311-x86_64-linux-gnu.so
chempotpy/ALC/ALC7m1_LEPS_ModelSurface.f
chempotpy/ALC/ALC7m1_LEPS_ModelSurface.log
chempotpy/ALC/ALC7m4_LEPS_ModelSurface.cpython-311-x86_64-linux-gnu.so
chempotpy/ALC/ALC7m4_LEPS_ModelSurface.f
chempotpy/ALC/ALC7m4_LEPS_ModelSurface.log
chempotpy/ALC/ALC7m5_LEPS_ModelSurface.cpython-311-x86_64-linux-gnu.so
chempotpy/ALC/ALC7m5_LEPS_ModelSurface.f
chempotpy/ALC/ALC7m5_LEPS_ModelSurface.log
chempotpy/ALC/ALC7m7_LEPS_ModelSurface.cpython-311-x86_64-linux-gnu.so
chempotpy/ALC/ALC7m7_LEPS_ModelSurface.f
chempotpy/ALC/ALC7m7_LEPS_ModelSurface.log
chempotpy/ALC/ALC7p2_LEPS_ModelSurface.cpython-311-x86_64-linux-gnu.so
chempotpy/ALC/ALC7p2_LEPS_ModelSurface.f
chempotpy/ALC/ALC7p2_LEPS_ModelSurface.log
chempotpy/ALC/ALC7p3_LEPS_ModelSurface.cpython-311-x86_64-linux-gnu.so
chempotpy/ALC/ALC7p3_LEPS_ModelSurface.f
chempotpy/ALC/ALC7p3_LEPS_ModelSurface.log
chempotpy/ALC/ALC7p5_LEPS_ModelSurface.cpython-311-x86_64-linux-gnu.so
chempotpy/ALC/ALC7p5_LEPS_ModelSurface.f
chempotpy/ALC/ALC7p5_LEPS_ModelSurface.log
chempotpy/ALC/ALC_LEPS_ModelSurface.cpython-311-x86_64-linux-gnu.so
chempotpy/ALC/ALC_LEPS_ModelSurface.f
chempotpy/ALC/ALC_LEPS_ModelSurface.log
chempotpy/ALC/__init__.py
chempotpy-1.0.7.dist-info/LICENSE
chempotpy-1.0.7.dist-info/METADATA
chempotpy-1.0.7.dist-info/WHEEL
chempotpy-1.0.7.dist-info/top_level.txt
chempotpy-1.0.7.dist-info/zip-safe
chempotpy-1.0.7.dist-info/RECORD
